napari_pdf_reader/__init__.py
napari_pdf_reader/_reader.py
napari_pdf_reader-0.0.1a3.dist-info/METADATA
napari_pdf_reader-0.0.1a3.dist-info/WHEEL
napari_pdf_reader-0.0.1a3.dist-info/entry_points.txt
napari_pdf_reader-0.0.1a3.dist-info/top_level.txt
napari_pdf_reader-0.0.1a3.dist-info/RECORD
